lxml/ElementInclude.py
lxml/__init__.py
lxml/_elementpath.cpython-37m-aarch64-linux-gnu.so
lxml/_elementpath.py
lxml/builder.cpython-37m-aarch64-linux-gnu.so
lxml/builder.py
lxml/cssselect.py
lxml/doctestcompare.py
lxml/etree.cpython-37m-aarch64-linux-gnu.so
lxml/etree.h
lxml/etree_api.h
lxml/lxml.etree.h
lxml/lxml.etree_api.h
lxml/objectify.cpython-37m-aarch64-linux-gnu.so
lxml/pyclasslookup.py
lxml/sax.cpython-37m-aarch64-linux-gnu.so
lxml/sax.py
lxml/usedoctest.py
lxml/html/ElementSoup.py
lxml/html/__init__.py
lxml/html/_diffcommand.py
lxml/html/_html5builder.py
lxml/html/_setmixin.py
lxml/html/builder.py
lxml/html/clean.cpython-37m-aarch64-linux-gnu.so
lxml/html/clean.py
lxml/html/defs.py
lxml/html/diff.cpython-37m-aarch64-linux-gnu.so
lxml/html/diff.py
lxml/html/formfill.py
lxml/html/html5parser.py
lxml/html/soupparser.py
lxml/html/usedoctest.py
lxml/includes/__init__.pxd
lxml/includes/__init__.py
lxml/includes/c14n.pxd
lxml/includes/config.pxd
lxml/includes/dtdvalid.pxd
lxml/includes/etree_defs.h
lxml/includes/etreepublic.pxd
lxml/includes/htmlparser.pxd
lxml/includes/lxml-version.h
lxml/includes/relaxng.pxd
lxml/includes/schematron.pxd
lxml/includes/tree.pxd
lxml/includes/uri.pxd
lxml/includes/xinclude.pxd
lxml/includes/xmlerror.pxd
lxml/includes/xmlparser.pxd
lxml/includes/xmlschema.pxd
lxml/includes/xpath.pxd
lxml/includes/xslt.pxd
lxml/isoschematron/__init__.py
lxml/isoschematron/resources/rng/iso-schematron.rng
lxml/isoschematron/resources/xsl/RNG2Schtrn.xsl
lxml/isoschematron/resources/xsl/XSD2Schtrn.xsl
lxml/isoschematron/resources/xsl/iso-schematron-xslt1/iso_abstract_expand.xsl
lxml/isoschematron/resources/xsl/iso-schematron-xslt1/iso_dsdl_include.xsl
lxml/isoschematron/resources/xsl/iso-schematron-xslt1/iso_schematron_message.xsl
lxml/isoschematron/resources/xsl/iso-schematron-xslt1/iso_schematron_skeleton_for_xslt1.xsl
lxml/isoschematron/resources/xsl/iso-schematron-xslt1/iso_svrl_for_xslt1.xsl
lxml_odidev-4.5.0.dist-info/LICENSE.txt
lxml_odidev-4.5.0.dist-info/LICENSES.txt
lxml_odidev-4.5.0.dist-info/METADATA
lxml_odidev-4.5.0.dist-info/WHEEL
lxml_odidev-4.5.0.dist-info/top_level.txt
lxml_odidev-4.5.0.dist-info/RECORD
