Metadata-Version: 2.1
Name: lxml-odidev
Version: 4.5.0
Summary: Powerful and Pythonic XML processing library combining libxml2/libxslt with the ElementTree API.
Home-page: https://lxml.de/
Author: lxml dev team
Author-email: lxml-dev@lxml.de
Maintainer: lxml dev team
Maintainer-email: lxml-dev@lxml.de
License: BSD
Platform: UNKNOWN
Classifier: Development Status :: 5 - Production/Stable
Classifier: Intended Audience :: Developers
Classifier: Intended Audience :: Information Technology
Classifier: License :: OSI Approved :: BSD License
Classifier: Programming Language :: Cython
Classifier: Programming Language :: Python :: 2
Classifier: Programming Language :: Python :: 2.7
Classifier: Programming Language :: Python :: 3
Classifier: Programming Language :: Python :: 3.5
Classifier: Programming Language :: Python :: 3.6
Classifier: Programming Language :: Python :: 3.7
Classifier: Programming Language :: Python :: 3.8
Classifier: Programming Language :: C
Classifier: Operating System :: OS Independent
Classifier: Topic :: Text Processing :: Markup :: HTML
Classifier: Topic :: Text Processing :: Markup :: XML
Classifier: Topic :: Software Development :: Libraries :: Python Modules
Requires-Python: >=2.7, !=3.0.*, !=3.1.*, !=3.2.*, !=3.3.*, != 3.4.*
Provides-Extra: cssselect
Requires-Dist: cssselect (>=0.7) ; extra == 'cssselect'
Provides-Extra: html5
Requires-Dist: html5lib ; extra == 'html5'
Provides-Extra: htmlsoup
Requires-Dist: BeautifulSoup4 ; extra == 'htmlsoup'
Provides-Extra: source
Requires-Dist: Cython (>=0.29.7) ; extra == 'source'
